intent_pilot-0.1.4.dist-info/METADATA
intent_pilot-0.1.4.dist-info/WHEEL
intent_pilot-0.1.4.dist-info/entry_points.txt
intent_pilot/__init__.py
intent_pilot/__main__.py
intent_pilot/run/__init__.py
intent_pilot/run/app.py
intent_pilot/utils/__init__.py
intent_pilot/utils/config.py
intent_pilot/utils/controller/__init__.py
intent_pilot/utils/controller/controller.py
intent_pilot/utils/controller/thought2command.py
intent_pilot/utils/encoding.py
intent_pilot/utils/font_assets/arial.ttf
intent_pilot/utils/img_utils.py
intent_pilot/utils/models/__init__.py
intent_pilot/utils/models/askui.py
intent_pilot/utils/models/gpt4.py
intent_pilot/utils/models/model_handler.py
intent_pilot/utils/models/prompts.py
intent_pilot/utils/screenshot.py
intent_pilot/utils/system_utils.py
intent_pilot/utils/terminal.py
intent_pilot/utils/viz_utils.py
intent_pilot-0.1.4.dist-info/RECORD
