Metadata-Version: 2.1
Name: intent-pilot
Version: 0.1.4
Summary: what can be said can be automated
Author-Email: gitlost-murali-askui <murali.kondragunta@askui.com>
License: MIT
Requires-Python: >=3.9
Requires-Dist: python-dotenv>=1.0.1
Requires-Dist: Pillow>=10.2.0
Requires-Dist: requests>=2.31.0
Requires-Dist: openai>=1.12.0
Requires-Dist: PyAutoGUI>=0.9.54
Requires-Dist: plyer>=2.1.0
Requires-Dist: prompt-toolkit>=3.0.43
Requires-Dist: fuzzywuzzy[speedup]>=0.18.0
Requires-Dist: pyperclip>=1.8.2
